sparc.cli-1.0.0-py2.7-nspkg.pth
sparc/cli/__init__.py
sparc/cli/command.py
sparc/cli/configure.zcml
sparc/cli/exceptions.py
sparc/cli/ftesting.zcml
sparc/cli/input.py
sparc/cli/interfaces.py
sparc/cli/testing.py
sparc/cli/tests/__init__.py
sparc/cli/tests/test_command.py
sparc/cli/tests/test_input.py
sparc.cli-1.0.0.dist-info/METADATA
sparc.cli-1.0.0.dist-info/RECORD
sparc.cli-1.0.0.dist-info/WHEEL
sparc.cli-1.0.0.dist-info/entry_points.txt
sparc.cli-1.0.0.dist-info/namespace_packages.txt
sparc.cli-1.0.0.dist-info/top_level.txt
